fabdocker/__init__.py
fabdocker/compose.py
fabdocker/docker.py
fabdocker-0.3.5.dist-info/DESCRIPTION.rst
fabdocker-0.3.5.dist-info/METADATA
fabdocker-0.3.5.dist-info/RECORD
fabdocker-0.3.5.dist-info/WHEEL
fabdocker-0.3.5.dist-info/metadata.json
fabdocker-0.3.5.dist-info/top_level.txt
