Metadata-Version: 2.0
Name: fabdocker
Version: 0.3.5
Summary: Deploy Docker containers with Fabric.
Home-page: https://github.com/DandyDev/fabdocker
Author: Daan Debie
Author-email: debie.daan@gmail.com
License: MIT
Platform: any
Classifier: Development Status :: 4 - Beta
Classifier: Environment :: Console
Classifier: Intended Audience :: Developers
Classifier: License :: OSI Approved :: MIT License
Classifier: Operating System :: POSIX
Classifier: Operating System :: MacOS
Classifier: Operating System :: Unix
Classifier: Programming Language :: Python
Classifier: Programming Language :: Python :: 2
Classifier: Topic :: Utilities
Requires-Dist: Fabric (==1.10.1)
